vprtempo/VPRTempo.py
vprtempo/VPRTempoQuant.py
vprtempo/VPRTempoQuantTrain.py
vprtempo/VPRTempoTrain.py
vprtempo/__init__.py
vprtempo/src/__init__.py
vprtempo/src/blitnet.py
vprtempo/src/create_data_csv.py
vprtempo/src/dataset.py
vprtempo/src/demo.py
vprtempo/src/download.py
vprtempo/src/loggers.py
vprtempo/src/metrics.py
vprtempo/src/nordland.py
vprtempo/src/process_orc.py
vprtempo-1.1.10.data/scripts/main.py
vprtempo-1.1.10.dist-info/licenses/LICENSE
vprtempo-1.1.10.dist-info/METADATA
vprtempo-1.1.10.dist-info/WHEEL
vprtempo-1.1.10.dist-info/top_level.txt
vprtempo-1.1.10.dist-info/RECORD
