Metadata-Version: 2.4
Name: VPRTempo
Version: 1.1.10
Summary: VPRTempo: A Fast Temporally Encoded Spiking Neural Network for Visual Place Recognition
Home-page: https://github.com/QVPR/VPRTempo
Author: Adam D Hines, Peter G Stratton, Michael Milford and Tobias Fischer
Author-email: adam.hines@qut.edu.au
License: MIT
Keywords: python,place recognition,spiking neural networks,computer vision,robotics
Classifier: Development Status :: 4 - Beta
Classifier: Intended Audience :: Developers
Classifier: License :: OSI Approved :: MIT License
Classifier: Programming Language :: Python :: 3.6
Classifier: Programming Language :: Python :: 3.7
Classifier: Programming Language :: Python :: 3.8
Classifier: Programming Language :: Python :: 3.9
Classifier: Programming Language :: Python :: 3.10
Classifier: Programming Language :: Python :: 3.11
Classifier: Programming Language :: Python :: 3.12
Requires-Python: >=3.6, <3.13
License-File: LICENSE
Requires-Dist: torch
Requires-Dist: torchvision
Requires-Dist: numpy
Requires-Dist: pandas
Requires-Dist: tqdm
Requires-Dist: prettytable
Requires-Dist: matplotlib
Requires-Dist: requests
Requires-Dist: imageio
Dynamic: author
Dynamic: author-email
Dynamic: classifier
Dynamic: description
Dynamic: description-content-type
Dynamic: home-page
Dynamic: keywords
Dynamic: license
Dynamic: license-file
Dynamic: requires-dist
Dynamic: requires-python
Dynamic: summary
